EQL_README.wiki
MANIFEST
README.rst
README.wiki
setup.cfg
setup.py
echo/__init__.py
echo/core_api.py
echo/kvs.py
echo/oauth2_headers.py
echo/settings.py
echo/users.py
echo/eql/__init__.py
echo/eql/filters.py
echo/eql/packaging_operators.py
echo/feeds/__init__.py
echo/feeds/parsers.py
echo/items/__init__.py
echo/items/mux_api.py
python_echo_streamserver.egg-info/PKG-INFO
python_echo_streamserver.egg-info/SOURCES.txt
python_echo_streamserver.egg-info/dependency_links.txt
python_echo_streamserver.egg-info/top_level.txt
samples/feeds.py
samples/kvs.py
samples/mux.py
samples/query.py
samples/send_account.py
samples/submit.py
samples/submit2.py
samples/submit3.py
samples/users.py
scripts/eql_shell
tests/__init__.py
tests/run.py
tests/test_eql.py
tests/test_feeds.py
tests/test_items.py
tests/test_kvs.py
tests/test_users.py