Metadata-Version: 1.0
Name: python-echo-streamserver
Version: 0.83
Summary: Echo StreamServer API Client
Home-page: http://code.google.com/p/python-echo-streamserver/
Author: Andrew Droffner
Author-email: adroffner@gmail.com
License: PSF Licensed
Download-URL: https://code.google.com/p/python-echo-streamserver/downloads/list
Platform: UNKNOWN
Classifier: Development Status :: 5 - Production/Stable
Classifier: Intended Audience :: Developers
Classifier: License :: OSI Approved :: Python Software Foundation License
Classifier: Natural Language :: English
Classifier: Operating System :: OS Independent
Classifier: Programming Language :: Python :: 2.5
Classifier: Programming Language :: Python :: 2.6
Classifier: Programming Language :: Python :: 2.7
